identify_logline/__init__.py
identify_logline/identify.py
identify_logline/identify_logline.py
identify_logline/schema.py
answerbook_identify_logline-0.0.1.dist-info/METADATA
answerbook_identify_logline-0.0.1.dist-info/WHEEL
answerbook_identify_logline-0.0.1.dist-info/entry_points.txt
answerbook_identify_logline-0.0.1.dist-info/top_level.txt
answerbook_identify_logline-0.0.1.dist-info/RECORD
